odoo/addons/sales_team_operating_unit/README.rst
odoo/addons/sales_team_operating_unit/__init__.py
odoo/addons/sales_team_operating_unit/__manifest__.py
odoo/addons/sales_team_operating_unit/models/__init__.py
odoo/addons/sales_team_operating_unit/models/crm_team.py
odoo/addons/sales_team_operating_unit/security/crm_security.xml
odoo/addons/sales_team_operating_unit/static/description/icon.png
odoo/addons/sales_team_operating_unit/tests/__init__.py
odoo/addons/sales_team_operating_unit/tests/test_crm_team_operating_unit.py
odoo/addons/sales_team_operating_unit/views/crm_team_view.xml
odoo11_addon_sales_team_operating_unit-11.0.1.0.0.dist-info/DESCRIPTION.rst
odoo11_addon_sales_team_operating_unit-11.0.1.0.0.dist-info/METADATA
odoo11_addon_sales_team_operating_unit-11.0.1.0.0.dist-info/RECORD
odoo11_addon_sales_team_operating_unit-11.0.1.0.0.dist-info/WHEEL
odoo11_addon_sales_team_operating_unit-11.0.1.0.0.dist-info/metadata.json
odoo11_addon_sales_team_operating_unit-11.0.1.0.0.dist-info/top_level.txt
